DAnki/DAnki.py
DAnki/exemples.py
DAnki-1.0.1.dist-info/LICENSE
DAnki-1.0.1.dist-info/METADATA
DAnki-1.0.1.dist-info/WHEEL
DAnki-1.0.1.dist-info/top_level.txt
DAnki-1.0.1.dist-info/RECORD
