Metadata-Version: 2.1
Name: DAnki
Version: 1.0.1
Summary: Automate deck creation for Anki to learn german
Home-page: https://github.com/dileivas/DAnki
Author: Diego Leivas
Author-email: dileivas@hotmail.com
License: MIT
Keywords: anki,flashcards,memorization,german,deutsch
Platform: UNKNOWN
Classifier: License :: OSI Approved :: MIT License
Classifier: Programming Language :: Python :: 3
Classifier: Programming Language :: Python :: 3.8
Requires-Dist: pandas
Requires-Dist: googletrans
Requires-Dist: pyenchant
Requires-Dist: requests
Requires-Dist: bs4
Requires-Dist: treetaggerwrapper
Requires-Dist: gtts
Requires-Dist: genanki
